lab10/capstone_school_zone/school_zone_controller.v
`timescale 1ns / 1ps

module school_zone_controller(
    input clk,
    input reset,
    input ped_request,
    input school_zone,
    output reg [2:0] main_light,
    output reg [2:0] side_light,
    output reg walk_light,
    output reg school_warning,
    output [2:0] state_dbg,
    output [3:0] timer_dbg
);
    localparam RED = 3'b100;
    localparam YELLOW = 3'b010;
    localparam GREEN = 3'b001;

    localparam MAIN_GREEN = 3'd0;
    localparam MAIN_YELLOW = 3'd1;
    localparam ALL_RED_TO_SIDE = 3'd2;
    localparam SIDE_GREEN = 3'd3;
    localparam SIDE_YELLOW = 3'd4;
    localparam ALL_RED_TO_MAIN = 3'd5;

    localparam MAIN_GREEN_NORMAL_TICKS = 4'd8;
    localparam MAIN_GREEN_PED_TICKS = 4'd3;
    localparam YELLOW_TICKS = 4'd2;
    localparam ALL_RED_TICKS = 4'd1;
    localparam SIDE_GREEN_NORMAL_TICKS = 4'd4;
    localparam SIDE_GREEN_SCHOOL_TICKS = 4'd7;

    reg [2:0] state;
    reg [3:0] timer;
    reg [3:0] limit;
    reg ped_pending;

    assign state_dbg = state;
    assign timer_dbg = timer;

    always @(*) begin
        main_light = RED;
        side_light = RED;
        walk_light = 1'b0;
        school_warning = school_zone;
        limit = YELLOW_TICKS;

        case (state)
            MAIN_GREEN: begin
                main_light = GREEN;
                side_light = RED;
                limit = (ped_pending || ped_request) ?
                    MAIN_GREEN_PED_TICKS : MAIN_GREEN_NORMAL_TICKS;
            end
            MAIN_YELLOW: begin
                main_light = YELLOW;
                side_light = RED;
                limit = YELLOW_TICKS;
            end
            ALL_RED_TO_SIDE: begin
                main_light = RED;
                side_light = RED;
                limit = ALL_RED_TICKS;
            end
            SIDE_GREEN: begin
                main_light = RED;
                side_light = GREEN;
                walk_light = 1'b1;
                limit = school_zone ?
                    SIDE_GREEN_SCHOOL_TICKS : SIDE_GREEN_NORMAL_TICKS;
            end
            SIDE_YELLOW: begin
                main_light = RED;
                side_light = YELLOW;
                limit = YELLOW_TICKS;
            end
            ALL_RED_TO_MAIN: begin
                main_light = RED;
                side_light = RED;
                limit = ALL_RED_TICKS;
            end
            default: begin
                main_light = GREEN;
                side_light = RED;
                limit = MAIN_GREEN_NORMAL_TICKS;
            end
        endcase
    end

    always @(posedge clk or posedge reset) begin
        if (reset) begin
            state <= MAIN_GREEN;
            timer <= 4'd0;
            ped_pending <= 1'b0;
        end else begin
            if (ped_request) begin
                ped_pending <= 1'b1;
            end

            if (timer >= limit - 4'd1) begin
                timer <= 4'd0;
                case (state)
                    MAIN_GREEN: state <= MAIN_YELLOW;
                    MAIN_YELLOW: state <= ALL_RED_TO_SIDE;
                    ALL_RED_TO_SIDE: state <= SIDE_GREEN;
                    SIDE_GREEN: begin
                        state <= SIDE_YELLOW;
                        ped_pending <= 1'b0;
                    end
                    SIDE_YELLOW: state <= ALL_RED_TO_MAIN;
                    ALL_RED_TO_MAIN: state <= MAIN_GREEN;
                    default: state <= MAIN_GREEN;
                endcase
            end else begin
                timer <= timer + 4'd1;
            end
        end
    end
endmodule

lab10/capstone_school_zone/tb_school_zone_controller.v
`timescale 1ns / 1ps

module tb_school_zone_controller;
    reg clk;
    reg reset;
    reg ped_request;
    reg school_zone;
    wire [2:0] main_light;
    wire [2:0] side_light;
    wire walk_light;
    wire school_warning;
    wire [2:0] state_dbg;
    wire [3:0] timer_dbg;
    wire safe;

    assign safe = !(main_light == 3'b001 && side_light == 3'b001);

    school_zone_controller uut (
        .clk(clk),
        .reset(reset),
        .ped_request(ped_request),
        .school_zone(school_zone),
        .main_light(main_light),
        .side_light(side_light),
        .walk_light(walk_light),
        .school_warning(school_warning),
        .state_dbg(state_dbg),
        .timer_dbg(timer_dbg)
    );

    initial begin
        clk = 1'b0;
        forever #5 clk = ~clk;
    end

    initial begin
        $dumpfile("school_zone_controller.vcd");
        $dumpvars(0, tb_school_zone_controller);

        $display("time reset ped school state timer main side walk warn safe");
        $monitor("%4t   %b    %b     %b     %d     %d   %b  %b   %b    %b    %b",
            $time, reset, ped_request, school_zone, state_dbg, timer_dbg,
            main_light, side_light, walk_light, school_warning, safe);

        reset = 1'b1;
        ped_request = 1'b0;
        school_zone = 1'b0;
        #12;

        reset = 1'b0;
        #190;

        ped_request = 1'b1;
        #20;
        ped_request = 1'b0;
        #90;

        school_zone = 1'b1;
        #70;

        ped_request = 1'b1;
        #10;
        ped_request = 1'b0;
        #80;

        reset = 1'b1;
        #10;
        reset = 1'b0;
        school_zone = 1'b0;
        #60;

        $finish;
    end
endmodule

lab10/capstone_school_zone/school_zone_controller.vcd
$date
	Tue Jul 21 10:59:24 2026
$end
$version
	Icarus Verilog
$end
$timescale
	1ps
$end
$scope module tb_school_zone_controller $end
$var wire 1 ! walk_light $end
$var wire 4 " timer_dbg [3:0] $end
$var wire 3 # state_dbg [2:0] $end
$var wire 3 $ side_light [2:0] $end
$var wire 1 % school_warning $end
$var wire 1 & safe $end
$var wire 3 ' main_light [2:0] $end
$var reg 1 ( clk $end
$var reg 1 ) ped_request $end
$var reg 1 * reset $end
$var reg 1 + school_zone $end
$scope module uut $end
$var wire 1 ( clk $end
$var wire 1 ) ped_request $end
$var wire 1 * reset $end
$var wire 1 + school_zone $end
$var wire 3 , state_dbg [2:0] $end
$var wire 4 - timer_dbg [3:0] $end
$var parameter 4 . ALL_RED_TICKS $end
$var parameter 3 / ALL_RED_TO_MAIN $end
$var parameter 3 0 ALL_RED_TO_SIDE $end
$var parameter 3 1 GREEN $end
$var parameter 3 2 MAIN_GREEN $end
$var parameter 4 3 MAIN_GREEN_NORMAL_TICKS $end
$var parameter 4 4 MAIN_GREEN_PED_TICKS $end
$var parameter 3 5 MAIN_YELLOW $end
$var parameter 3 6 RED $end
$var parameter 3 7 SIDE_GREEN $end
$var parameter 4 8 SIDE_GREEN_NORMAL_TICKS $end
$var parameter 4 9 SIDE_GREEN_SCHOOL_TICKS $end
$var parameter 3 : SIDE_YELLOW $end
$var parameter 3 ; YELLOW $end
$var parameter 4 < YELLOW_TICKS $end
$var reg 4 = limit [3:0] $end
$var reg 3 > main_light [2:0] $end
$var reg 1 ? ped_pending $end
$var reg 1 % school_warning $end
$var reg 3 @ side_light [2:0] $end
$var reg 3 A state [2:0] $end
$var reg 4 B timer [3:0] $end
$var reg 1 ! walk_light $end
$upscope $end
$upscope $end
$enddefinitions $end
$comment Show the parameter values. $end
$dumpall
b10 <
b10 ;
b100 :
b111 9
b100 8
b11 7
b100 6
b1 5
b11 4
b1000 3
b0 2
b1 1
b10 0
b101 /
b1 .
$end
#0
$dumpvars
b0 B
b0 A
b100 @
0?
b1 >
b1000 =
b0 -
b0 ,
0+
1*
0)
0(
b1 '
1&
0%
b100 $
b0 #
b0 "
0!
$end
#5000
1(
#10000
0(
#12000
0*
#15000
b1 "
b1 -
b1 B
1(
#20000
0(
#25000
b10 "
b10 -
b10 B
1(
#30000
0(
#35000
b11 "
b11 -
b11 B
1(
#40000
0(
#45000
b100 "
b100 -
b100 B
1(
#50000
0(
#55000
b101 "
b101 -
b101 B
1(
#60000
0(
#65000
b110 "
b110 -
b110 B
1(
#70000
0(
#75000
b111 "
b111 -
b111 B
1(
#80000
0(
#85000
b10 =
b10 '
b10 >
b1 #
b1 ,
b1 A
b0 "
b0 -
b0 B
1(
#90000
0(
#95000
b1 "
b1 -
b1 B
1(
#100000
0(
#105000
b1 =
b100 '
b100 >
b10 #
b10 ,
b10 A
b0 "
b0 -
b0 B
1(
#110000
0(
#115000
1!
b1 $
b1 @
b100 =
b11 #
b11 ,
b11 A
1(
#120000
0(
#125000
b1 "
b1 -
b1 B
1(
#130000
0(
#135000
b10 "
b10 -
b10 B
1(
#140000
0(
#145000
b11 "
b11 -
b11 B
1(
#150000
0(
#155000
b10 =
0!
b10 $
b10 @
b100 #
b100 ,
b100 A
b0 "
b0 -
b0 B
1(
#160000
0(
#165000
b1 "
b1 -
b1 B
1(
#170000
0(
#175000
b1 =
b100 $
b100 @
b101 #
b101 ,
b101 A
b0 "
b0 -
b0 B
1(
#180000
0(
#185000
b1 '
b1 >
b1000 =
b0 #
b0 ,
b0 A
1(
#190000
0(
#195000
b1 "
b1 -
b1 B
1(
#200000
0(
#202000
b11 =
b1 '
b1 >
1)
#205000
b11 =
b1 '
b1 >
b10 "
b10 -
b10 B
1?
1(
#210000
0(
#215000
b10 =
b10 '
b10 >
b1 #
b1 ,
b1 A
b0 "
b0 -
b0 B
1(
#220000
0(
#222000
b10 '
b10 >
0)
#225000
b1 "
b1 -
b1 B
1(
#230000
0(
#235000
b1 =
b100 '
b100 >
b10 #
b10 ,
b10 A
b0 "
b0 -
b0 B
1(
#240000
0(
#245000
1!
b1 $
b1 @
b100 =
b11 #
b11 ,
b11 A
1(
#250000
0(
#255000
b1 "
b1 -
b1 B
1(
#260000
0(
#265000
b10 "
b10 -
b10 B
1(
#270000
0(
#275000
b11 "
b11 -
b11 B
1(
#280000
0(
#285000
b10 =
0!
b10 $
b10 @
0?
b100 #
b100 ,
b100 A
b0 "
b0 -
b0 B
1(
#290000
0(
#295000
b1 "
b1 -
b1 B
1(
#300000
0(
#305000
b1 =
b100 $
b100 @
b101 #
b101 ,
b101 A
b0 "
b0 -
b0 B
1(
#310000
0(
#312000
b1 =
1%
1+
#315000
b1 '
b1 >
b1000 =
b0 #
b0 ,
b0 A
1(
#320000
0(
#325000
b1 "
b1 -
b1 B
1(
#330000
0(
#335000
b10 "
b10 -
b10 B
1(
#340000
0(
#345000
b11 "
b11 -
b11 B
1(
#350000
0(
#355000
b100 "
b100 -
b100 B
1(
#360000
0(
#365000
b101 "
b101 -
b101 B
1(
#370000
0(
#375000
b110 "
b110 -
b110 B
1(
#380000
0(
#382000
b11 =
b1 '
b1 >
1)
#385000
b10 =
b10 '
b10 >
b1 #
b1 ,
b1 A
b0 "
b0 -
b0 B
1?
1(
#390000
0(
#392000
b10 '
b10 >
0)
#395000
b1 "
b1 -
b1 B
1(
#400000
0(
#405000
b1 =
b100 '
b100 >
b10 #
b10 ,
b10 A
b0 "
b0 -
b0 B
1(
#410000
0(
#415000
1!
b1 $
b1 @
b111 =
b11 #
b11 ,
b11 A
1(
#420000
0(
#425000
b1 "
b1 -
b1 B
1(
#430000
0(
#435000
b10 "
b10 -
b10 B
1(
#440000
0(
#445000
b11 "
b11 -
b11 B
1(
#450000
0(
#455000
b100 "
b100 -
b100 B
1(
#460000
0(
#465000
b101 "
b101 -
b101 B
1(
#470000
0(
#472000
b1 '
b1 >
b1000 =
0!
b100 $
b100 @
0?
b0 "
b0 -
b0 B
b0 #
b0 ,
b0 A
1*
#475000
1(
#480000
0(
#482000
b1000 =
0%
b1 '
b1 >
0+
0*
#485000
b1 "
b1 -
b1 B
1(
#490000
0(
#495000
b10 "
b10 -
b10 B
1(
#500000
0(
#505000
b11 "
b11 -
b11 B
1(
#510000
0(
#515000
b100 "
b100 -
b100 B
1(
#520000
0(
#525000
b101 "
b101 -
b101 B
1(
#530000
0(
#535000
b110 "
b110 -
b110 B
1(
