lab03/adders.v
`timescale 1ns / 1ps

module half_adder(
    input a,
    input b,
    output sum,
    output carry
);
    assign sum = a ^ b;
    assign carry = a & b;
endmodule

module full_adder(
    input a,
    input b,
    input cin,
    output sum,
    output cout
);
    wire sum_ab;
    wire carry_ab;
    wire carry_cin;

    half_adder ha0 (.a(a), .b(b), .sum(sum_ab), .carry(carry_ab));
    half_adder ha1 (.a(sum_ab), .b(cin), .sum(sum), .carry(carry_cin));

    assign cout = carry_ab | carry_cin;
endmodule

module adder_4bit(
    input [3:0] a,
    input [3:0] b,
    input cin,
    output [3:0] sum,
    output cout
);
    wire c1;
    wire c2;
    wire c3;

    full_adder fa0 (.a(a[0]), .b(b[0]), .cin(cin), .sum(sum[0]), .cout(c1));
    full_adder fa1 (.a(a[1]), .b(b[1]), .cin(c1), .sum(sum[1]), .cout(c2));
    full_adder fa2 (.a(a[2]), .b(b[2]), .cin(c2), .sum(sum[2]), .cout(c3));
    full_adder fa3 (.a(a[3]), .b(b[3]), .cin(c3), .sum(sum[3]), .cout(cout));
endmodule

module adder_8bit(
    input [7:0] a,
    input [7:0] b,
    input cin,
    output [7:0] sum,
    output cout
);
    wire c1;
    wire c2;
    wire c3;
    wire c4;
    wire c5;
    wire c6;
    wire c7;

    full_adder fa0 (.a(a[0]), .b(b[0]), .cin(cin), .sum(sum[0]), .cout(c1));
    full_adder fa1 (.a(a[1]), .b(b[1]), .cin(c1), .sum(sum[1]), .cout(c2));
    full_adder fa2 (.a(a[2]), .b(b[2]), .cin(c2), .sum(sum[2]), .cout(c3));
    full_adder fa3 (.a(a[3]), .b(b[3]), .cin(c3), .sum(sum[3]), .cout(c4));
    full_adder fa4 (.a(a[4]), .b(b[4]), .cin(c4), .sum(sum[4]), .cout(c5));
    full_adder fa5 (.a(a[5]), .b(b[5]), .cin(c5), .sum(sum[5]), .cout(c6));
    full_adder fa6 (.a(a[6]), .b(b[6]), .cin(c6), .sum(sum[6]), .cout(c7));
    full_adder fa7 (.a(a[7]), .b(b[7]), .cin(c7), .sum(sum[7]), .cout(cout));
endmodule

lab03/tb_adders.v
`timescale 1ns / 1ps

module tb_adders;
    reg a;
    reg b;
    reg cin;
    wire ha_sum;
    wire ha_carry;
    wire sum;
    wire cout;

    reg [3:0] a4;
    reg [3:0] b4;
    reg cin4;
    wire [3:0] sum4;
    wire cout4;

    reg [7:0] a8;
    reg [7:0] b8;
    reg cin8;
    wire [7:0] sum8;
    wire cout8;

    integer i;

    half_adder ha (.a(a), .b(b), .sum(ha_sum), .carry(ha_carry));
    full_adder fa (.a(a), .b(b), .cin(cin), .sum(sum), .cout(cout));
    adder_4bit add4 (.a(a4), .b(b4), .cin(cin4), .sum(sum4), .cout(cout4));
    adder_8bit add8 (.a(a8), .b(b8), .cin(cin8), .sum(sum8), .cout(cout8));

    initial begin
        $dumpfile("lab03_adders.vcd");
        $dumpvars(0, tb_adders);

        $display("Full adder truth table");
        $display("a b cin | sum cout");

        for (i = 0; i < 8; i = i + 1) begin
            {a, b, cin} = i[2:0];
            #10;
            $display("%b %b  %b  |  %b    %b", a, b, cin, sum, cout);
        end

        $display("4-bit adder checks");
        a4 = 4'd3;  b4 = 4'd5;  cin4 = 1'b0; #10;
        $display("%d + %d + %d = %d carry=%b", a4, b4, cin4, sum4, cout4);

        a4 = 4'd9;  b4 = 4'd7;  cin4 = 1'b0; #10;
        $display("%d + %d + %d = %d carry=%b", a4, b4, cin4, sum4, cout4);

        a4 = 4'd15; b4 = 4'd15; cin4 = 1'b1; #10;
        $display("%d + %d + %d = %d carry=%b", a4, b4, cin4, sum4, cout4);

        $display("8-bit adder challenge checks");
        a8 = 8'd3;   b8 = 8'd5;   cin8 = 1'b0; #10;
        $display("%d + %d + %d = %d carry=%b", a8, b8, cin8, sum8, cout8);

        a8 = 8'd127; b8 = 8'd1;   cin8 = 1'b0; #10;
        $display("%d + %d + %d = %d carry=%b", a8, b8, cin8, sum8, cout8);

        a8 = 8'd255; b8 = 8'd255; cin8 = 1'b1; #10;
        $display("%d + %d + %d = %d carry=%b", a8, b8, cin8, sum8, cout8);

        $finish;
    end
endmodule

lab03/lab03_adders.vcd
$date
	Tue Jul  7 11:07:40 2026
$end
$version
	Icarus Verilog
$end
$timescale
	1ps
$end
$scope module tb_adders $end
$var wire 8 ! sum8 [7:0] $end
$var wire 4 " sum4 [3:0] $end
$var wire 1 # sum $end
$var wire 1 $ ha_sum $end
$var wire 1 % ha_carry $end
$var wire 1 & cout8 $end
$var wire 1 ' cout4 $end
$var wire 1 ( cout $end
$var reg 1 ) a $end
$var reg 4 * a4 [3:0] $end
$var reg 8 + a8 [7:0] $end
$var reg 1 , b $end
$var reg 4 - b4 [3:0] $end
$var reg 8 . b8 [7:0] $end
$var reg 1 / cin $end
$var reg 1 0 cin4 $end
$var reg 1 1 cin8 $end
$var integer 32 2 i [31:0] $end
$scope module add4 $end
$var wire 4 3 a [3:0] $end
$var wire 4 4 b [3:0] $end
$var wire 1 0 cin $end
$var wire 4 5 sum [3:0] $end
$var wire 1 ' cout $end
$var wire 1 6 c3 $end
$var wire 1 7 c2 $end
$var wire 1 8 c1 $end
$scope module fa0 $end
$var wire 1 9 a $end
$var wire 1 : b $end
$var wire 1 0 cin $end
$var wire 1 8 cout $end
$var wire 1 ; sum_ab $end
$var wire 1 < sum $end
$var wire 1 = carry_cin $end
$var wire 1 > carry_ab $end
$scope module ha0 $end
$var wire 1 9 a $end
$var wire 1 : b $end
$var wire 1 > carry $end
$var wire 1 ; sum $end
$upscope $end
$scope module ha1 $end
$var wire 1 ; a $end
$var wire 1 0 b $end
$var wire 1 = carry $end
$var wire 1 < sum $end
$upscope $end
$upscope $end
$scope module fa1 $end
$var wire 1 ? a $end
$var wire 1 @ b $end
$var wire 1 8 cin $end
$var wire 1 7 cout $end
$var wire 1 A sum_ab $end
$var wire 1 B sum $end
$var wire 1 C carry_cin $end
$var wire 1 D carry_ab $end
$scope module ha0 $end
$var wire 1 ? a $end
$var wire 1 @ b $end
$var wire 1 D carry $end
$var wire 1 A sum $end
$upscope $end
$scope module ha1 $end
$var wire 1 A a $end
$var wire 1 8 b $end
$var wire 1 C carry $end
$var wire 1 B sum $end
$upscope $end
$upscope $end
$scope module fa2 $end
$var wire 1 E a $end
$var wire 1 F b $end
$var wire 1 7 cin $end
$var wire 1 6 cout $end
$var wire 1 G sum_ab $end
$var wire 1 H sum $end
$var wire 1 I carry_cin $end
$var wire 1 J carry_ab $end
$scope module ha0 $end
$var wire 1 E a $end
$var wire 1 F b $end
$var wire 1 J carry $end
$var wire 1 G sum $end
$upscope $end
$scope module ha1 $end
$var wire 1 G a $end
$var wire 1 7 b $end
$var wire 1 I carry $end
$var wire 1 H sum $end
$upscope $end
$upscope $end
$scope module fa3 $end
$var wire 1 K a $end
$var wire 1 L b $end
$var wire 1 6 cin $end
$var wire 1 ' cout $end
$var wire 1 M sum_ab $end
$var wire 1 N sum $end
$var wire 1 O carry_cin $end
$var wire 1 P carry_ab $end
$scope module ha0 $end
$var wire 1 K a $end
$var wire 1 L b $end
$var wire 1 P carry $end
$var wire 1 M sum $end
$upscope $end
$scope module ha1 $end
$var wire 1 M a $end
$var wire 1 6 b $end
$var wire 1 O carry $end
$var wire 1 N sum $end
$upscope $end
$upscope $end
$upscope $end
$scope module add8 $end
$var wire 8 Q a [7:0] $end
$var wire 8 R b [7:0] $end
$var wire 1 1 cin $end
$var wire 8 S sum [7:0] $end
$var wire 1 & cout $end
$var wire 1 T c7 $end
$var wire 1 U c6 $end
$var wire 1 V c5 $end
$var wire 1 W c4 $end
$var wire 1 X c3 $end
$var wire 1 Y c2 $end
$var wire 1 Z c1 $end
$scope module fa0 $end
$var wire 1 [ a $end
$var wire 1 \ b $end
$var wire 1 1 cin $end
$var wire 1 Z cout $end
$var wire 1 ] sum_ab $end
$var wire 1 ^ sum $end
$var wire 1 _ carry_cin $end
$var wire 1 ` carry_ab $end
$scope module ha0 $end
$var wire 1 [ a $end
$var wire 1 \ b $end
$var wire 1 ` carry $end
$var wire 1 ] sum $end
$upscope $end
$scope module ha1 $end
$var wire 1 ] a $end
$var wire 1 1 b $end
$var wire 1 _ carry $end
$var wire 1 ^ sum $end
$upscope $end
$upscope $end
$scope module fa1 $end
$var wire 1 a a $end
$var wire 1 b b $end
$var wire 1 Z cin $end
$var wire 1 Y cout $end
$var wire 1 c sum_ab $end
$var wire 1 d sum $end
$var wire 1 e carry_cin $end
$var wire 1 f carry_ab $end
$scope module ha0 $end
$var wire 1 a a $end
$var wire 1 b b $end
$var wire 1 f carry $end
$var wire 1 c sum $end
$upscope $end
$scope module ha1 $end
$var wire 1 c a $end
$var wire 1 Z b $end
$var wire 1 e carry $end
$var wire 1 d sum $end
$upscope $end
$upscope $end
$scope module fa2 $end
$var wire 1 g a $end
$var wire 1 h b $end
$var wire 1 Y cin $end
$var wire 1 X cout $end
$var wire 1 i sum_ab $end
$var wire 1 j sum $end
$var wire 1 k carry_cin $end
$var wire 1 l carry_ab $end
$scope module ha0 $end
$var wire 1 g a $end
$var wire 1 h b $end
$var wire 1 l carry $end
$var wire 1 i sum $end
$upscope $end
$scope module ha1 $end
$var wire 1 i a $end
$var wire 1 Y b $end
$var wire 1 k carry $end
$var wire 1 j sum $end
$upscope $end
$upscope $end
$scope module fa3 $end
$var wire 1 m a $end
$var wire 1 n b $end
$var wire 1 X cin $end
$var wire 1 W cout $end
$var wire 1 o sum_ab $end
$var wire 1 p sum $end
$var wire 1 q carry_cin $end
$var wire 1 r carry_ab $end
$scope module ha0 $end
$var wire 1 m a $end
$var wire 1 n b $end
$var wire 1 r carry $end
$var wire 1 o sum $end
$upscope $end
$scope module ha1 $end
$var wire 1 o a $end
$var wire 1 X b $end
$var wire 1 q carry $end
$var wire 1 p sum $end
$upscope $end
$upscope $end
$scope module fa4 $end
$var wire 1 s a $end
$var wire 1 t b $end
$var wire 1 W cin $end
$var wire 1 V cout $end
$var wire 1 u sum_ab $end
$var wire 1 v sum $end
$var wire 1 w carry_cin $end
$var wire 1 x carry_ab $end
$scope module ha0 $end
$var wire 1 s a $end
$var wire 1 t b $end
$var wire 1 x carry $end
$var wire 1 u sum $end
$upscope $end
$scope module ha1 $end
$var wire 1 u a $end
$var wire 1 W b $end
$var wire 1 w carry $end
$var wire 1 v sum $end
$upscope $end
$upscope $end
$scope module fa5 $end
$var wire 1 y a $end
$var wire 1 z b $end
$var wire 1 V cin $end
$var wire 1 U cout $end
$var wire 1 { sum_ab $end
$var wire 1 | sum $end
$var wire 1 } carry_cin $end
$var wire 1 ~ carry_ab $end
$scope module ha0 $end
$var wire 1 y a $end
$var wire 1 z b $end
$var wire 1 ~ carry $end
$var wire 1 { sum $end
$upscope $end
$scope module ha1 $end
$var wire 1 { a $end
$var wire 1 V b $end
$var wire 1 } carry $end
$var wire 1 | sum $end
$upscope $end
$upscope $end
$scope module fa6 $end
$var wire 1 !" a $end
$var wire 1 "" b $end
$var wire 1 U cin $end
$var wire 1 T cout $end
$var wire 1 #" sum_ab $end
$var wire 1 $" sum $end
$var wire 1 %" carry_cin $end
$var wire 1 &" carry_ab $end
$scope module ha0 $end
$var wire 1 !" a $end
$var wire 1 "" b $end
$var wire 1 &" carry $end
$var wire 1 #" sum $end
$upscope $end
$scope module ha1 $end
$var wire 1 #" a $end
$var wire 1 U b $end
$var wire 1 %" carry $end
$var wire 1 $" sum $end
$upscope $end
$upscope $end
$scope module fa7 $end
$var wire 1 '" a $end
$var wire 1 (" b $end
$var wire 1 T cin $end
$var wire 1 & cout $end
$var wire 1 )" sum_ab $end
$var wire 1 *" sum $end
$var wire 1 +" carry_cin $end
$var wire 1 ," carry_ab $end
$scope module ha0 $end
$var wire 1 '" a $end
$var wire 1 (" b $end
$var wire 1 ," carry $end
$var wire 1 )" sum $end
$upscope $end
$scope module ha1 $end
$var wire 1 )" a $end
$var wire 1 T b $end
$var wire 1 +" carry $end
$var wire 1 *" sum $end
$upscope $end
$upscope $end
$upscope $end
$scope module fa $end
$var wire 1 ) a $end
$var wire 1 , b $end
$var wire 1 / cin $end
$var wire 1 ( cout $end
$var wire 1 -" sum_ab $end
$var wire 1 # sum $end
$var wire 1 ." carry_cin $end
$var wire 1 /" carry_ab $end
$scope module ha0 $end
$var wire 1 ) a $end
$var wire 1 , b $end
$var wire 1 /" carry $end
$var wire 1 -" sum $end
$upscope $end
$scope module ha1 $end
$var wire 1 -" a $end
$var wire 1 / b $end
$var wire 1 ." carry $end
$var wire 1 # sum $end
$upscope $end
$upscope $end
$scope module ha $end
$var wire 1 ) a $end
$var wire 1 , b $end
$var wire 1 % carry $end
$var wire 1 $ sum $end
$upscope $end
$upscope $end
$enddefinitions $end
$comment Show the parameter values. $end
$dumpall
$end
#0
$dumpvars
0/"
0."
0-"
x,"
x+"
x*"
x)"
x("
x'"
x&"
x%"
x$"
x#"
x""
x!"
x~
x}
x|
x{
xz
xy
xx
xw
xv
xu
xt
xs
xr
xq
xp
xo
xn
xm
xl
xk
xj
xi
xh
xg
xf
xe
xd
xc
xb
xa
x`
x_
x^
x]
x\
x[
xZ
xY
xX
xW
xV
xU
xT
bx S
bx R
bx Q
xP
xO
xN
xM
xL
xK
xJ
xI
xH
xG
xF
xE
xD
xC
xB
xA
x@
x?
x>
x=
x<
x;
x:
x9
x8
x7
x6
bx 5
bx 4
bx 3
b0 2
x1
x0
0/
bx .
bx -
0,
bx +
bx *
0)
0(
x'
x&
0%
0$
0#
bx "
bx !
$end
#10000
1#
1/
b1 2
#20000
1-"
1$
1#
1,
0/
b10 2
#30000
1(
0#
1."
1/
b11 2
#40000
0(
1#
0."
1)
0,
0/
b100 2
#50000
1(
0#
1."
1/
b101 2
#60000
0-"
1/"
0$
1%
0#
0."
1,
0/
b110 2
#70000
1#
1/
b111 2
#80000
1N
16
0H
1I
17
0'
0<
b1000 "
b1000 5
0B
1C
0O
18
0;
1>
1A
0D
1G
0J
0M
0P
0=
1:
0@
1F
0L
19
1?
0E
0K
00
b101 -
b101 4
b11 *
b11 3
b1000 2
#90000
1'
b0 "
b0 5
0N
1O
1M
1@
0?
1K
b111 -
b111 4
b1001 *
b1001 3
#100000
1N
0O
1B
0C
1H
0I
0M
1P
0A
1D
0G
1J
b1111 "
b1111 5
1<
1L
1?
1E
10
b1111 -
b1111 4
b1111 *
b1111 3
#110000
1p
1X
0j
1k
0v
0|
0$"
0*"
1Y
0W
0V
0U
0T
0&
0^
b1000 !
b1000 S
0d
1e
0q
0w
0}
0%"
0+"
1Z
0]
1`
1c
0f
1i
0l
0o
0r
0u
0x
0{
0~
0#"
0&"
0)"
0,"
0_
1\
0b
1h
0n
0t
0z
0""
0("
1[
1a
0g
0m
0s
0y
0!"
0'"
01
b101 .
b101 R
b11 +
b11 Q
#120000
1*"
1T
1%"
1U
1}
1V
1w
1W
0p
1q
0v
0|
b10000000 !
b10000000 S
0$"
1o
1u
1{
1#"
0h
1g
1m
1s
1y
1!"
b1 .
b1 R
b1111111 +
b1111111 Q
#130000
1d
0e
1j
0k
1p
0q
1v
0w
1|
0}
1$"
0%"
1&
0c
1f
0i
1l
0o
1r
0u
1x
0{
1~
0#"
1&"
1,"
b11111111 !
b11111111 S
1^
1b
1h
1n
1t
1z
1""
1("
1'"
11
b11111111 .
b11111111 R
b11111111 +
b11111111 Q
