lab09/lab09/sequence_detector.v
`timescale 1ns / 1ps

module sequence_detector_1101(
    input clk,
    input reset,
    input bit_in,
    output reg detected
);
    localparam S_RESET = 3'd0;
    localparam S_1 = 3'd1;
    localparam S_11 = 3'd2;
    localparam S_110 = 3'd3;
    localparam S_1101 = 3'd4;

    reg [2:0] state;
    reg [2:0] next_state;

    always @(*) begin
        case (state)
            S_RESET: next_state = bit_in ? S_1 : S_RESET;
            S_1: next_state = bit_in ? S_11 : S_RESET;
            S_11: next_state = bit_in ? S_11 : S_110;
            S_110: next_state = bit_in ? S_1101 : S_RESET;
            S_1101: next_state = bit_in ? S_11 : S_RESET;
            default: next_state = S_RESET;
        endcase
    end

    always @(*) begin
        detected = (state == S_1101);
    end

    always @(posedge clk or posedge reset) begin
        if (reset) begin
            state <= S_RESET;
        end else begin
            state <= next_state;
        end
    end
endmodule

lab09/lab09/tb_sequence_detector.v
`timescale 1ns / 1ps

module tb_sequence_detector;
    reg clk;
    reg reset;
    reg bit_in;
    wire detected;

    reg [15:0] stream;
    integer i;

    sequence_detector_1101 uut (
        .clk(clk),
        .reset(reset),
        .bit_in(bit_in),
        .detected(detected)
    );

    initial begin
        clk = 1'b0;
        forever #5 clk = ~clk;
    end

    initial begin
        $dumpfile("lab09_sequence_detector.vcd");
        $dumpvars(0, tb_sequence_detector);

        reset = 1'b1;
        bit_in = 1'b0;
        stream = 16'b1101_0110_1101_1101;
        #12;
        reset = 1'b0;

        for (i = 15; i >= 0; i = i - 1) begin
            bit_in = stream[i];
            #10;
            $display("bit=%b detected=%b", bit_in, detected);
        end

        $finish;
    end
endmodule

lab09/lab09/lab09_sequence_detector.vcd
$date
	Tue Jul 14 12:37:35 2026
$end
$version
	Icarus Verilog
$end
$timescale
	1ps
$end
$scope module tb_sequence_detector $end
$var wire 1 ! detected $end
$var reg 1 " bit_in $end
$var reg 1 # clk $end
$var reg 1 $ reset $end
$var reg 16 % stream [15:0] $end
$var integer 32 & i [31:0] $end
$scope module uut $end
$var wire 1 " bit_in $end
$var wire 1 # clk $end
$var wire 1 $ reset $end
$var parameter 3 ' S_1 $end
$var parameter 3 ( S_11 $end
$var parameter 3 ) S_110 $end
$var parameter 3 * S_1101 $end
$var parameter 3 + S_RESET $end
$var reg 1 ! detected $end
$var reg 3 , next_state [2:0] $end
$var reg 3 - state [2:0] $end
$upscope $end
$upscope $end
$enddefinitions $end
$comment Show the parameter values. $end
$dumpall
b0 +
b100 *
b11 )
b10 (
b1 '
$end
#0
$dumpvars
b0 -
b0 ,
bx &
b1101011011011101 %
1$
0#
0"
0!
$end
#5000
1#
#10000
0#
#12000
b1 ,
1"
b1111 &
0$
#15000
b10 ,
b1 -
1#
#20000
0#
#22000
b1110 &
#25000
b10 -
1#
#30000
0#
#32000
b11 ,
0"
b1101 &
#35000
b0 ,
b11 -
1#
#40000
0#
#42000
b100 ,
1"
b1100 &
#45000
1!
b10 ,
b100 -
1#
#50000
0#
#52000
b0 ,
0"
b1011 &
#55000
0!
b0 -
1#
#60000
0#
#62000
b1 ,
1"
b1010 &
#65000
b10 ,
b1 -
1#
#70000
0#
#72000
b1001 &
#75000
b10 -
1#
#80000
0#
#82000
b11 ,
0"
b1000 &
#85000
b0 ,
b11 -
1#
#90000
0#
#92000
b100 ,
1"
b111 &
#95000
1!
b10 ,
b100 -
1#
#100000
0#
#102000
b110 &
#105000
0!
b10 -
1#
#110000
0#
#112000
b11 ,
0"
b101 &
#115000
b0 ,
b11 -
1#
#120000
0#
#122000
b100 ,
1"
b100 &
#125000
1!
b10 ,
b100 -
1#
#130000
0#
#132000
b11 &
#135000
0!
b10 -
1#
#140000
0#
#142000
b10 &
#145000
1#
#150000
0#
#152000
b11 ,
0"
b1 &
#155000
b0 ,
b11 -
1#
#160000
0#
#162000
b100 ,
1"
b0 &
#165000
1!
b10 ,
b100 -
1#
#170000
0#
#172000
b11111111111111111111111111111111 &
